odoo/addons/fieldservice_agreement_repair/README.rst
odoo/addons/fieldservice_agreement_repair/__init__.py
odoo/addons/fieldservice_agreement_repair/__manifest__.py
odoo/addons/fieldservice_agreement_repair/i18n/fieldservice_agreement_repair.pot
odoo/addons/fieldservice_agreement_repair/i18n/it.po
odoo/addons/fieldservice_agreement_repair/models/__init__.py
odoo/addons/fieldservice_agreement_repair/models/fsm_order.py
odoo/addons/fieldservice_agreement_repair/readme/CONTRIBUTORS.md
odoo/addons/fieldservice_agreement_repair/readme/DESCRIPTION.md
odoo/addons/fieldservice_agreement_repair/readme/USAGE.md
odoo/addons/fieldservice_agreement_repair/static/description/icon.png
odoo/addons/fieldservice_agreement_repair/static/description/icon.svg
odoo/addons/fieldservice_agreement_repair/static/description/index.html
odoo/addons/fieldservice_agreement_repair/tests/__init__.py
odoo/addons/fieldservice_agreement_repair/tests/test_fieldservice_agreement_repair.py
odoo_addon_fieldservice_agreement_repair-17.0.1.0.0.3.dist-info/METADATA
odoo_addon_fieldservice_agreement_repair-17.0.1.0.0.3.dist-info/WHEEL
odoo_addon_fieldservice_agreement_repair-17.0.1.0.0.3.dist-info/top_level.txt
odoo_addon_fieldservice_agreement_repair-17.0.1.0.0.3.dist-info/RECORD
