Metadata-Version: 2.1
Name: odoo-addon-fieldservice_agreement_repair
Version: 17.0.1.0.0.3
Requires-Python: >=3.10
Requires-Dist: odoo-addon-agreement_repair>=17.0dev,<17.1dev
Requires-Dist: odoo-addon-fieldservice_agreement>=17.0dev,<17.1dev
Requires-Dist: odoo-addon-fieldservice_repair>=17.0dev,<17.1dev
Requires-Dist: odoo>=17.0a,<17.1dev
Summary: Fieldservice Agreement Repair
Home-page: https://github.com/OCA/field-service
License: AGPL-3
Author: Camptocamp SA, Italo Lopes, Odoo Community Association (OCA)
Author-email: support@odoo-community.org
Classifier: Programming Language :: Python
Classifier: Framework :: Odoo
Classifier: Framework :: Odoo :: 17.0
Classifier: License :: OSI Approved :: GNU Affero General Public License v3
